{
  "sections": {
    "16372498804121dda9": {
      "type": "split-screen-slider",
      "blocks": {
        "1637249880c19b891c-2": {
          "type": "slide",
          "settings": {
            "tagline": "Introducing",
            "title": "Our brand new store",
            "subtitle": "Showcase your best products",
            "button_label": "Explore all",
            "button_link": "",
            "seo_h_tag": "h2"
          }
        },
        "1637249880c19b891c-0": {
          "type": "slide",
          "settings": {
            "tagline": "Why not",
            "title": "Write about yourself",
            "subtitle": "Include some awesome images",
            "button_label": "Learn more",
            "button_link": "shopify:\/\/collections\/new-os2-0",
            "seo_h_tag": "h2"
          }
        },
        "1637249880c19b891c-1": {
          "type": "slide",
          "settings": {
            "tagline": "Take the opportunity to",
            "title": "Promote your products",
            "subtitle": "Include various promotions and flash sales",
            "button_label": "Shop now",
            "button_link": "",
            "seo_h_tag": "h2"
          }
        }
      },
      "block_order": [
        "1637249880c19b891c-2",
        "1637249880c19b891c-0",
        "1637249880c19b891c-1"
      ],
      "disabled": true,
      "settings": {
        "desktop_layout": "split",
        "desktop_image_positioning": "image-on-left",
        "desktop_text": "rgba(0,0,0,0)",
        "desktop_background": "#ebebed",
        "desktop_overlay": "rgba(0,0,0,0)",
        "mobile_height": "var(--window-height)",
        "mobile_text": "#ffffff",
        "mobile_background": "#000000",
        "heading_size": "h1"
      }
    },
    "16371348113d6d6d6d": {
      "type": "collection-list",
      "blocks": {
        "1637134811779b275e-0": {
          "type": "collection",
          "settings": {
            "collection": "mens",
            "image": "shopify:\/\/shop_images\/Group_8.png"
          }
        },
        "1637134811779b275e-1": {
          "type": "collection",
          "settings": {
            "collection": "women",
            "image": "shopify:\/\/shop_images\/Group_9.png"
          }
        },
        "1637134811779b275e-2": {
          "type": "collection",
          "settings": {
            "collection": "accessories",
            "image": "shopify:\/\/shop_images\/Group_7.png"
          }
        },
        "72b2baec-beba-441e-be59-19891ef57dd5": {
          "type": "collection",
          "settings": {
            "collection": "frontpage"
          }
        }
      },
      "block_order": [
        "1637134811779b275e-0",
        "1637134811779b275e-1",
        "1637134811779b275e-2",
        "72b2baec-beba-441e-be59-19891ef57dd5"
      ],
      "settings": {
        "title": "Our Collections",
        "text_alignment": "horizontal-left vertical-bottom",
        "custom_background": "#eeeeef",
        "custom_text": "rgba(0,0,0,0)",
        "bg_overlay": false,
        "seo_h_tag": "h2"
      }
    }
  },
  "order": [
    "16372498804121dda9",
    "16371348113d6d6d6d"
  ]
}
